{"js":"const chart = Highcharts.chart('container', {\n    title: {\n        text: 'Remove cropped point'\n    },\n    subtitle: {\n        text: 'Click button to remove a point [0, 0] and shift zoom to verify that it is removed'\n    },\n    xAxis: {\n        min: 100\n    },\n    series: [{\n        data: (function (arr, i) {\n            for (i = 0; i < 200; i = i + 1) {\n                arr.push(i);\n            }\n            return arr;\n        }([])),\n        cropThreshold: 100\n    }]\n\n});\n\ndocument.getElementById('remove').addEventListener('click', () => {\n    chart.series[0].removePoint(0);\n\n    chart.xAxis[0].setExtremes(0, 100); // Verify that point [0, 0] is removed\n});\n","css":"#container {\n    height: 400px;\n    min-width: 310px;\n    max-width: 800px;\n}\n","html":"\n<div id=\"container\"></div>\n<button id=\"remove\" class=\"autocompare\">Remove point and pan</button>","npm":"// 安装\nnpm install highcharts@10.3.2 --save\n\n// import 模块 \nimport Highcharts from 'highcharts';\nimport Zh_cn      from 'https://code.hcharts.cn/plugins/zh_cn.js';\n\n// 初始化模块\nZh_cn(Highcharts);\n","scripts":["https://code.hcharts.cn/10.3.2/highcharts.js","https://code.hcharts.cn/plugins/zh_cn.js"]}