{"js":"const chart = Highcharts.chart('container', {\n    xAxis: {\n        categories: ['Apples', 'Pears', 'Bananas', 'Oranges']\n    },\n    series: [{\n        data: [1, 11, 209, 0.2],\n        type: 'column'\n    }]\n});\n\nlet isLogarithmic = false;\ndocument.getElementById('linlog').addEventListener('click', () => {\n    chart.yAxis[0].update({\n        type: isLogarithmic ? 'linear' : 'logarithmic'\n    });\n    isLogarithmic = !isLogarithmic;\n});\n","css":"#container {\n    min-width: 300px;\n    max-width: 800px;\n    height: 300px;\n    margin: 1em auto;\n}\n","html":"\n<div id=\"container\"></div>\n<button id=\"linlog\">Toggle linear/logarithmic</button>\n","npm":"// 安装\nnpm install highcharts@10.3.2 --save\n\n// import 模块 \nimport Highcharts from 'highcharts';\nimport Zh_cn      from 'https://code.hcharts.cn/plugins/zh_cn.js';\n\n// 初始化模块\nZh_cn(Highcharts);\n","scripts":["https://code.hcharts.cn/10.3.2/highcharts.js","https://code.hcharts.cn/plugins/zh_cn.js"]}