{"js":"Highcharts.chart('container', {\n    chart: {\n        type: 'packedbubble',\n        height: '100%'\n    },\n    title: {\n        text: 'Carbon emissions around the world (2014)'\n    },\n    tooltip: {\n        useHTML: true,\n        pointFormat: '<b>{point.name}:</b> {point.y}m CO<sub>2</sub>'\n    },\n    plotOptions: {\n        packedbubble: {\n            marker: {\n                fillColor: {\n                    radialGradient: { cx: 0.4, cy: 0.3, r: 0.7 },\n                    stops: [\n                        [0, 'rgba(255,255,255,0.5)'],\n                        [1, Highcharts.color(Highcharts.getOptions().colors[0]).setOpacity(0.5).get('rgba')]\n                    ]\n                }\n            },\n            minSize: '20%',\n            maxSize: '80%',\n            layoutAlgorithm: {\n                initialPositionRadius: 100,\n                splitSeries: true,\n                parentNodeLimit: true,\n                parentNodeOptions: {\n                    marker: {\n                        fillColor: {\n                            radialGradient: { cx: 0.4, cy: 0.3, r: 0.7 },\n                            stops: [\n                                [0, 'rgba(255,255,255,0.5)'],\n                                [1, Highcharts.color('#00ff00').setOpacity(0.5).get('rgba')]\n                            ]\n                        },\n                        fillOpacity: 0.5,\n                        lineWidth: 0\n                    }\n                }\n            },\n            dataLabels: {\n                enabled: true,\n                format: '{point.name}',\n                filter: {\n                    property: 'y',\n                    operator: '>',\n                    value: 250\n                },\n                style: {\n                    color: 'black',\n                    textOutline: 'none',\n                    fontWeight: 'normal'\n                }\n            }\n        }\n    },\n    series: [{\n        name: 'Europe',\n        color: '#220000',\n        data: [{\n            name: 'Germany',\n            value: 767.1\n        }, {\n            name: 'Croatia',\n            value: 20.7\n        },\n        {\n            name: \"Belgium\",\n            value: 97.2\n        },\n        {\n            name: \"Czech Republic\",\n            value: 111.7\n        },\n        {\n            name: \"Netherlands\",\n            value: 158.1\n        },\n        {\n            name: \"Spain\",\n            value: 241.6\n        },\n        {\n            name: \"Ukraine\",\n            value: 249.1\n        },\n        {\n            name: \"Poland\",\n            value: 298.1\n        },\n        {\n            name: \"France\",\n            value: 323.7\n        },\n        {\n            name: \"Romania\",\n            value: 78.3\n        },\n        {\n            name: \"United Kingdom\",\n            value: 415.4\n        }, {\n            name: \"Turkey\",\n            value: 353.2\n        }, {\n            name: \"Italy\",\n            value: 337.6\n        },\n        {\n            name: \"Greece\",\n            value: 71.1\n        },\n        {\n            name: \"Austria\",\n            value: 69.8\n        },\n        {\n            name: \"Belarus\",\n            value: 67.7\n        },\n        {\n            name: \"Serbia\",\n            value: 59.3\n        },\n        {\n            name: \"Finland\",\n            value: 54.8\n        },\n        {\n            name: \"Bulgaria\",\n            value: 51.2\n        },\n        {\n            name: \"Portugal\",\n            value: 48.3\n        },\n        {\n            name: \"Norway\",\n            value: 44.4\n        },\n        {\n            name: \"Sweden\",\n            value: 44.3\n        },\n        {\n            name: \"Hungary\",\n            value: 43.7\n        },\n        {\n            name: \"Switzerland\",\n            value: 40.2\n        },\n        {\n            name: \"Denmark\",\n            value: 40\n        },\n        {\n            name: \"Slovakia\",\n            value: 34.7\n        },\n        {\n            name: \"Ireland\",\n            value: 34.6\n        },\n        {\n            name: \"Croatia\",\n            value: 20.7\n        },\n        {\n            name: \"Estonia\",\n            value: 19.4\n        },\n        {\n            name: \"Slovenia\",\n            value: 16.7\n        },\n        {\n            name: \"Lithuania\",\n            value: 12.3\n        },\n        {\n            name: \"Luxembourg\",\n            value: 10.4\n        },\n        {\n            name: \"Macedonia\",\n            value: 9.5\n        },\n        {\n            name: \"Moldova\",\n            value: 7.8\n        },\n        {\n            name: \"Latvia\",\n            value: 7.5\n        },\n        {\n            name: \"Cyprus\",\n            value: 7.2\n        }]\n    }]\n});\n","css":"#container {\n    min-width: 320px;\n    max-width: 800px;\n    margin: 0 auto;\n}\n","html":"\n<div id=\"container\"></div>","npm":"// 安装\nnpm install highcharts@10.3.2 --save\n\n// import 模块 \nimport Highcharts      from 'highcharts';\nimport HighchartsMore  from 'highcharts/highcharts-more';\nimport Exporting       from 'highcharts/modules/exporting';\nimport HighchartsZh_CN from 'https://code.hcharts.cn/plugins/highcharts-zh_CN.js';\n\n// 初始化模块\nHighchartsMore(Highcharts);\nExporting(Highcharts);\nHighchartsZh_CN(Highcharts);\n","scripts":["https://code.hcharts.cn/10.3.2/highcharts.js","https://code.hcharts.cn/10.3.2/highcharts-more.js","https://code.hcharts.cn/10.3.2/modules/exporting.js","https://code.hcharts.cn/plugins/highcharts-zh_CN.js"]}