{"js":"// Create the chart\nHighcharts.chart('container', {\n    chart: {\n        type: 'column'\n    },\n    title: {\n        text: 'Highcharts multi-series drilldown'\n    },\n    subtitle: {\n        text: 'The <em>allowPointDrilldown</em> option makes point clicks drill to the whole category'\n    },\n    xAxis: {\n        type: 'category'\n    },\n\n    plotOptions: {\n        series: {\n            borderWidth: 0,\n            dataLabels: {\n                enabled: true\n            }\n        }\n    },\n\n    series: [{\n        name: '2010',\n        data: [{\n            name: 'Republican',\n            y: 5,\n            drilldown: 'republican-2010'\n        }, {\n            name: 'Democrats',\n            y: 2,\n            drilldown: 'democrats-2010'\n        }, {\n            name: 'Other',\n            y: 4,\n            drilldown: 'other-2010'\n        }]\n    }, {\n        name: '2014',\n        data: [{\n            name: 'Republican',\n            y: 4,\n            drilldown: 'republican-2014'\n        }, {\n            name: 'Democrats',\n            y: 4,\n            drilldown: 'democrats-2014'\n        }, {\n            name: 'Other',\n            y: 4,\n            drilldown: 'other-2014'\n        }]\n    }],\n    drilldown: {\n        allowPointDrilldown: false,\n        series: [{\n            id: 'republican-2010',\n            name: 'Republican 2010',\n            data: [\n                ['East', 4],\n                ['West', 2],\n                ['North', 1],\n                ['South', 4]\n            ]\n        }, {\n            id: 'democrats-2010',\n            name: 'Republican 2010',\n            data: [\n                ['East', 6],\n                ['West', 2],\n                ['North', 2],\n                ['South', 4]\n            ]\n        }, {\n            id: 'other-2010',\n            name: 'Other 2010',\n            data: [\n                ['East', 2],\n                ['West', 7],\n                ['North', 3],\n                ['South', 2]\n            ]\n        }, {\n            id: 'republican-2014',\n            name: 'Republican 2014',\n            data: [\n                ['East', 2],\n                ['West', 4],\n                ['North', 1],\n                ['South', 7]\n            ]\n        }, {\n            id: 'democrats-2014',\n            name: 'Democrats 2014',\n            data: [\n                ['East', 4],\n                ['West', 2],\n                ['North', 5],\n                ['South', 3]\n            ]\n        }, {\n            id: 'other-2014',\n            name: 'Other 2014',\n            data: [\n                ['East', 7],\n                ['West', 8],\n                ['North', 2],\n                ['South', 2]\n            ]\n        }]\n    }\n});\n","css":"#container {\n    min-width: 310px;\n    height: 400px;\n    margin: 0 auto;\n}\n","html":"\n<div id=\"container\"></div>\n","npm":"// 安装\nnpm install highcharts@11.0.0 --save\n\n// import 模块 \nimport Highcharts from 'highcharts';\nimport Drilldown  from 'highcharts/modules/drilldown';\n\n// 初始化模块\nDrilldown(Highcharts);\n","scripts":["https://code.highcharts.com/11.0.0/highcharts.js","https://code.highcharts.com/11.0.0/modules/drilldown.js"]}