{"js":"/**\n * Add custom date formats\n */\nHighcharts.dateFormats.W = function (timestamp) {\n    var date = new Date(timestamp),\n        day = date.getUTCDay() === 0 ? 7 : date.getUTCDay(),\n        dayNumber;\n\n    date.setDate(date.getUTCDate() + 4 - day);\n    dayNumber = Math.floor((date.getTime() - new Date(date.getUTCFullYear(), 0, 1, -6)) / 86400000);\n\n    return 1 + Math.floor(dayNumber / 7);\n};\n\nHighcharts.chart('container', {\n\n    title: {\n        text: 'Custom date format'\n    },\n\n    xAxis: {\n        type: 'datetime',\n        tickInterval: 7 * 24 * 36e5, // one week\n        labels: {\n            format: '{value:Week %W/%Y}',\n            align: 'right',\n            rotation: -30\n        }\n    },\n\n    series: [{\n        data: [29.9, 71.5, 106.4, 129.2, 144.0, 176.0, 135.6, 148.5, 216.4, 194.1, 95.6, 54.4],\n        pointInterval: 7 * 24 * 36e5,\n        pointStart: Date.UTC(2013, 0, 7)\n\n    }]\n\n});","css":"#container {\n    height: 400px;\n}\n","html":"\n<div id=\"container\"></div>","npm":"// 安装\nnpm install highcharts@10.3.2 --save\n\n// import 模块 \nimport Highcharts      from 'highcharts';\nimport HighchartsZh_CN from 'https://code.hcharts.cn/plugins/highcharts-zh_CN.js';\n\n// 初始化模块\nHighchartsZh_CN(Highcharts);\n","scripts":["https://code.hcharts.cn/10.3.2/highcharts.js","https://code.hcharts.cn/plugins/highcharts-zh_CN.js"]}