{"js":"Highcharts.chart('container', {\n\n    title: {\n        text: 'Highcharts Annotations'\n    },\n\n    subtitle: {\n        text: 'Annotation label presentation options'\n    },\n\n    series: [{\n        keys: ['y', 'id'],\n        data: [[29.9, '0'], [71.5, '1'], [106.4, '2'], [129.2, '3'], [144.0, '4'], [176.0, '5']]\n    }],\n\n    tooltip: {\n        enabled: false\n    },\n\n    annotations: [{\n        labels: [{\n            point: '0',\n            shadow: true\n        }, {\n            point: '1',\n            shadow: {\n                color: 'red',\n                offsetX: -1,\n                opacity: 0.3\n            }\n        }, {\n            point: '2',\n            padding: 10\n        }, {\n            point: '3',\n            style: {\n                fontSize: '8px'\n            }\n        }, {\n            point: '4',\n            borderWidth: 3\n        }, {\n            point: '5'\n        }],\n        labelOptions: {\n            borderRadius: 5,\n            backgroundColor: 'rgba(252, 255, 197, 0.7)',\n            borderWidth: 1,\n            borderColor: '#AAA'\n        }\n    }]\n});","css":"#container {\n    height: 400px;\n    max-width: 800px;\n    margin: 0 auto;\n}\n","html":"\n<div id=\"container\"></div>\n","npm":"// 安装\nnpm install highcharts@11.0.0 --save\n\n// import 模块 \nimport Highcharts  from 'highcharts';\nimport Annotations from 'highcharts/modules/annotations';\n\n// 初始化模块\nAnnotations(Highcharts);\n","scripts":["https://code.highcharts.com/11.0.0/highcharts.js","https://code.highcharts.com/11.0.0/modules/annotations.js"]}