{"js":"Highcharts.getJSON('https://cdn.jsdelivr.net/gh/highcharts/highcharts@v10.3.3/samples/data/usdeur.json', function (data) {\n\n    var lastDate = data[data.length - 1][0],  // Get year of last data point\n        days = 24 * 36e5; // Milliseconds in a day\n\n    // Create the chart\n    Highcharts.stockChart('container', {\n\n        rangeSelector: {\n            selected: 1\n        },\n\n        title: {\n            text: 'USD to EUR exchange rate'\n        },\n\n        yAxis: [{\n            title: {\n                text: 'Exchange rate'\n            },\n            top: '15%',\n            height: '85%'\n        }, {\n            height: '15%'\n        }],\n\n        plotOptions: {\n            flags: {\n                accessibility: {\n                    exposeAsGroupOnly: true,\n                    description: 'Flagged events.'\n                }\n            }\n        },\n\n        series: [{\n            name: 'USD to EUR',\n            data: data,\n            id: 'dataseries',\n            tooltip: {\n                valueDecimals: 4\n            }\n        }, {\n            type: 'flags',\n            name: 'Flags on series',\n            data: [{\n                x: lastDate - 60 * days,\n                title: 'On series'\n            }, {\n                x: lastDate - 30 * days,\n                title: 'On series'\n            }],\n            onSeries: 'dataseries',\n            shape: 'squarepin'\n        }, {\n            type: 'flags',\n            name: 'Flags on axis',\n            data: [{\n                x: lastDate - 45 * days,\n                title: 'On axis'\n            }, {\n                x: lastDate - 15 * days,\n                title: 'On axis'\n            }],\n            shape: 'squarepin'\n        }, {\n            type: 'flags',\n            name: 'Flags in pane',\n            data: [{\n                x: lastDate - 40 * days,\n                title: 'In pane'\n            }, {\n                x: lastDate - 15 * days,\n                title: 'In pane'\n            }],\n            yAxis: 1,\n            shape: 'squarepin'\n        }]\n    });\n});","css":"#container {\n    height: 400px;\n    min-width: 310px;\n}\n","html":"\n\n<div id=\"container\"></div>","npm":"// 安装\nnpm install highcharts@11.0.0 --save\n\n// import 模块 \nimport Highcharts    from 'highcharts/highstock';\nimport Data          from 'highcharts/modules/data';\nimport Exporting     from 'highcharts/modules/exporting';\nimport Accessibility from 'highcharts/modules/accessibility';\n\n// 初始化模块\nData(Highcharts);\nExporting(Highcharts);\nAccessibility(Highcharts);\n","scripts":["https://code.highcharts.com/stock/11.0.0/highstock.js","https://code.highcharts.com/stock/11.0.0/modules/data.js","https://code.highcharts.com/stock/11.0.0/modules/exporting.js","https://code.highcharts.com/11.0.0/modules/accessibility.js"]}