{"js":"const chart = Highcharts.stockChart('container', {\n    rangeSelector: {\n        selected: 1\n    },\n\n    series: [{\n        name: 'USD to EUR',\n        data: usdeur\n    }]\n});\n\ndocument.getElementById('button').addEventListener('click', () => {\n    chart.xAxis[0].setExtremes(\n        Date.UTC(2014, 0, 1),\n        Date.UTC(2014, 11, 31)\n    );\n});\n","css":"#container {\n    height: 400px;\n    min-width: 600px;\n}\n","html":"<div id=\"container\"></div>\n\n<button id=\"button\" class=\"autocompare\">Show 2014</button>\n\n","npm":"// 安装\nnpm install highcharts@11.0.1 --save\n\n// import 模块 \nimport Highcharts from 'highcharts/highstock';\nimport Exporting  from 'highcharts/modules/exporting';\nimport Usdeur     from 'https://www.highcharts.com/samples/data/usdeur.js';\n\n// 初始化模块\nExporting(Highcharts);\nUsdeur(Highcharts);\n","scripts":["https://code.highcharts.com/stock/11.0.1/highstock.js","https://code.highcharts.com/stock/11.0.1/modules/exporting.js","https://www.highcharts.com/samples/data/usdeur.js"]}