{"js":"Highcharts.setOptions({\n    global: {\n        useUTC: false\n    }\n});\n\n// Create the chart\nHighcharts.stockChart('container', {\n    chart: {\n        events: {\n            load: function () {\n\n                // set up the updating of the chart each second\n                var series = this.series[0];\n                setInterval(function () {\n                    var y = Math.round(Math.random() * 100);\n                    series.addPoint(y, true, true);\n                }, 1000);\n            }\n        }\n    },\n\n    rangeSelector: {\n        buttons: [{\n            count: 1,\n            type: 'minute',\n            text: '1M'\n        }, {\n            count: 5,\n            type: 'minute',\n            text: '5M'\n        }, {\n            type: 'all',\n            text: 'All'\n        }],\n        inputEnabled: false,\n        selected: 0\n    },\n\n    title: {\n        text: 'Live random data with overscroll'\n    },\n\n    exporting: {\n        enabled: false\n    },\n\n    xAxis: {\n        overscroll: 10 * 1000 // 10 seconds\n    },\n\n    navigator: {\n        xAxis: {\n            overscroll: 10 * 1000 // 10 seconds\n        }\n    },\n\n    series: [{\n        name: 'Random data',\n        pointStart: Date.UTC(2017, 0, 1),\n        pointInterval: 1000, // 1s\n        data: (function () {\n            // generate an array of random data\n            var data = [],\n                i;\n\n            for (i = 0; i <= 1000; i += 1) {\n                data.push(\n                    Math.round(Math.random() * 100)\n                );\n            }\n            return data;\n        }())\n    }]\n});\n","css":"#container {\n    height: 400px;\n    min-width: 600px;\n}\n","html":"<div id=\"container\"></div>\n\n","npm":"// 安装\nnpm install highcharts@11.0.0 --save\n\n// import 模块 \nimport Highcharts from 'highcharts/highstock';\nimport Exporting  from 'highcharts/modules/exporting';\n\n// 初始化模块\nExporting(Highcharts);\n","scripts":["https://code.highcharts.com/stock/11.0.0/highstock.js","https://code.highcharts.com/stock/11.0.0/modules/exporting.js"]}