{"js":"(async () => {\n\n    const topology = await fetch(\n        'https://code.highcharts.com/mapdata/custom/europe.topo.json'\n    ).then(response => response.json());\n\n    Highcharts.mapChart('container', {\n        chart: {\n            map: topology\n        },\n        colorAxis: {\n            dataClasses: [{\n                from: 0,\n                to: 2\n            }, {\n                from: 2,\n                to: 4\n            }, {\n                from: 4\n            }]\n        },\n        series: [{\n            data: [\n                ['is', 1],\n                ['no', 2],\n                ['se', 3],\n                ['dk', 4],\n                ['fi', 5]\n            ]\n        }]\n    });\n\n})();","css":"#container {\n    height: 500px;\n    min-width: 310px;\n    max-width: 800px;\n    margin: 1em auto;\n}\n\ninput:focus {\n    outline: 3px solid red;\n}\n\ncaption {\n    padding-bottom: 5px;\n    font-family: Verdana, sans-serif;\n    font-size: 14pt;\n    font-weight: bold;\n    color: #555;\n}\n\ntable {\n    font-family: Verdana, sans-serif;\n    font-size: 12pt;\n    color: #555;\n    border-collapse: collapse;\n    border: 3px solid #ccc;\n    margin: 2px auto;\n}\n\ntr {\n    border-bottom: 2px solid #eee;\n}\n\nth {\n    border-left: 2px solid #eee;\n    border-right: 2px solid #eee;\n    padding: 12px 15px;\n    border-collapse: collapse;\n}\n\nth[scope=\"col\"] {\n    background-color: #ffe;\n}\n\nth[scope=\"row\"] {\n    background-color: #f0fcff;\n    text-align: left;\n}\n\ntd {\n    border-left: 2px solid #eee;\n    border-right: 2px solid #eee;\n    padding: 12px 15px;\n    border-collapse: collapse;\n}\n","html":"\n<input value=\"click to focus\">\n<div id=\"container\"></div>\n<input value=\"after chart\">\n","npm":"// 安装\nnpm install highcharts@11.0.0 --save\n\n// import 模块 \nimport Highcharts    from 'highcharts/highmaps';\nimport Accessibility from 'highcharts/modules/accessibility';\n\n// 初始化模块\nAccessibility(Highcharts);\n","scripts":["https://code.highcharts.com/maps/11.0.0/highmaps.js","https://code.highcharts.com/11.0.0/modules/accessibility.js"]}