{"js":"Highcharts.chart('container', {\n    series: [{\n        connectors: {\n            marker: {\n                enabled: true\n            }\n        },\n        data: [{\n            x: 10,\n            y: 10,\n            id: 'center'\n        }, {\n            x: 10,\n            y: 5,\n            connect: 'center'\n        }, {\n            x: 15,\n            y: 5,\n            connect: 'center'\n        }, {\n            x: 15,\n            y: 10,\n            connect: 'center'\n        }, {\n            x: 15,\n            y: 15,\n            connect: 'center'\n        }, {\n            x: 10,\n            y: 15,\n            connect: 'center'\n        }, {\n            x: 5,\n            y: 15,\n            connect: 'center'\n        }, {\n            x: 5,\n            y: 10,\n            connect: 'center'\n        }, {\n            x: 5,\n            y: 5,\n            connect: 'center'\n        }],\n        type: 'scatter'\n    }]\n});\n","css":"#container {\n    max-width: 800px;\n    height: 400px;\n    margin: 1em auto;\n}\n","html":"\n<div id=\"container\"></div>\n","npm":"// 安装\nnpm install highcharts@11.0.1 --save\n\n// import 模块 \nimport Highcharts from 'highcharts';\nimport Pathfinder from 'highcharts/modules/pathfinder';\n\n// 初始化模块\nPathfinder(Highcharts);\n","scripts":["https://code.highcharts.com/gantt/11.0.1/highcharts.js","https://code.highcharts.com/gantt/11.0.1/modules/pathfinder.js"]}